django_hint/__init__.py
django_hint/typehint.py
django_hint-0.3.2.dist-info/LICENSE
django_hint-0.3.2.dist-info/METADATA
django_hint-0.3.2.dist-info/WHEEL
django_hint-0.3.2.dist-info/top_level.txt
django_hint-0.3.2.dist-info/RECORD
