Metadata-Version: 2.1
Name: django_hint
Version: 0.3.2
Summary: Type hinting package for django
Home-page: https://github.com/Vieolo/django-hint
Author: Vieolo OÜ
Author-email: info@vieolo.com
Classifier: Programming Language :: Python :: 3.6
Classifier: License :: OSI Approved :: MIT License
Classifier: Operating System :: OS Independent
License-File: LICENSE
